synthesize/__init__.py
synthesize/__main__.py
synthesize/cli.py
synthesize/config.py
synthesize/constants.py
synthesize/execution.py
synthesize/messages.py
synthesize/model.py
synthesize/orchestrator.py
synthesize/py.typed
synthesize/renderer.py
synthesize/state.py
synthesize/utils.py
synthesize-0.0.6.dist-info/METADATA
synthesize-0.0.6.dist-info/WHEEL
synthesize-0.0.6.dist-info/entry_points.txt
synthesize-0.0.6.dist-info/licenses/LICENSE
synthesize-0.0.6.dist-info/RECORD
